[{"id":532150694,"progress":[0,1,1,1,1],"title":"MAJOR ORDER","briefing":"The Automatons are attempting to reclaim the territory held by their initial Vanguard. They must be stopped.","description":"Designated planets must be under Super Earth control when order expires.","tasks":[{"type":13,"values":[1,1,154],"valueTypes":[3,11,12]},{"type":13,"values":[1,1,155],"valueTypes":[3,11,12]},{"type":13,"values":[1,1,107],"valueTypes":[3,11,12]},{"type":13,"values":[1,1,197],"valueTypes":[3,11,12]},{"type":13,"values":[1,1,153],"valueTypes":[3,11,12]}],"reward":{"type":1,"amount":45},"expiration":"2024-06-26T09:26:34.5703016Z"}]