[{"id":1071750134,"progress":[0],"title":"MAJOR ORDER","briefing":"Liberate more planets than are lost in order to repel the grotesque Terminid swarm, and prevent the fascist monsters from capitalizing on the hatched spawn befouling our finest citizens.","description":null,"tasks":[{"type":15,"values":[1],"valueTypes":[3]}],"reward":{"type":1,"amount":55},"rewards":[{"type":1,"amount":55}],"expiration":"2026-03-02T14:44:05.7140614Z","flags":1},{"id":1050821185,"progress":[1],"title":"STRATEGIC OPPORTUNITY","briefing":"Defend Oshaune from Terminid re-infestation and secure the planet's Stratagem stockpile.","description":null,"tasks":[{"type":13,"values":[1,1,212],"valueTypes":[3,11,12]}],"reward":null,"rewards":[],"expiration":"2026-03-01T16:09:26.7141233Z","flags":1}]